jam/__abc_instances__.py
jam/__deprecated__.py
jam/__init__.py
jam/__logger__.py
jam/instance.py
jam/modules.py
jam/aio/__init__.py
jam/aio/instance.py
jam/aio/modules.py
jam/aio/jwt/__init__.py
jam/aio/jwt/tools.py
jam/aio/jwt/lists/__init__.py
jam/aio/jwt/lists/json.py
jam/aio/jwt/lists/redis.py
jam/aio/oauth2/__init__.py
jam/aio/oauth2/client.py
jam/aio/oauth2/builtin/__init__.py
jam/aio/oauth2/builtin/github.py
jam/aio/oauth2/builtin/gitlab.py
jam/aio/oauth2/builtin/google.py
jam/aio/oauth2/builtin/yandex.py
jam/aio/sessions/__init__.py
jam/aio/sessions/json.py
jam/aio/sessions/redis.py
jam/exceptions/__init__.py
jam/exceptions/jwt.py
jam/exceptions/oauth2.py
jam/exceptions/sessions.py
jam/ext/__init__.py
jam/ext/fastapi/__init__.py
jam/ext/flask/__init__.py
jam/ext/flask/extensions.py
jam/ext/litestar/__init__.py
jam/ext/litestar/middlewares.py
jam/ext/litestar/plugins.py
jam/ext/litestar/value.py
jam/ext/starlette/__init__.py
jam/ext/starlette/auth_backends.py
jam/ext/starlette/value.py
jam/jwt/__init__.py
jam/jwt/__utils__.py
jam/jwt/tools.py
jam/jwt/types.py
jam/jwt/lists/__abc_list_repo__.py
jam/jwt/lists/__init__.py
jam/jwt/lists/json.py
jam/jwt/lists/redis.py
jam/oauth2/__abc_oauth2_repo__.py
jam/oauth2/__init__.py
jam/oauth2/client.py
jam/oauth2/builtin/__init__.py
jam/oauth2/builtin/github.py
jam/oauth2/builtin/gitlab.py
jam/oauth2/builtin/google.py
jam/oauth2/builtin/yandex.py
jam/otp/__abc_module__.py
jam/otp/__init__.py
jam/otp/hotp.py
jam/otp/totp.py
jam/quick/__init__.py
jam/quick/jwt.py
jam/sessions/__abc_session_repo__.py
jam/sessions/__init__.py
jam/sessions/json.py
jam/sessions/redis.py
jam/tests/__init__.py
jam/tests/clients.py
jam/tests/fakers.py
jam/utils/__init__.py
jam/utils/aes.py
jam/utils/await_maybe.py
jam/utils/config_maker.py
jam/utils/otp_keys.py
jam/utils/rsa.py
jam/utils/salt_hash.py
jam/utils/xor.py
jamlib-2.5.5.dist-info/licenses/LICENSE.md
jamlib-2.5.5.dist-info/METADATA
jamlib-2.5.5.dist-info/WHEEL
jamlib-2.5.5.dist-info/top_level.txt
jamlib-2.5.5.dist-info/RECORD
