Metadata-Version: 2.4
Name: jamlib
Version: 2.5.5
Summary: Simple and universal library for authorization.
Author-email: Makridenko Adrian <adrianmakridenko@duck.com>, Ksenia Travnikova <kseniatravnikova@duck.com>
License: MIT License
Project-URL: Homepage, https://jam.makridenko.ru
Project-URL: Repository, https://github.com/lyaguxafrog/jam
Project-URL: Issues, https://github.com/lyaguxafrog/jam/issues
Project-URL: Changelog, https://github.com/lyaguxafrog/jam/releases
Keywords: Authentication,Backend,JWT,Sessions,OTP,TOTP,OAuth2,Litestar,FastAPI,Starlette,Flask
Classifier: License :: OSI Approved :: MIT License
Classifier: Development Status :: 5 - Production/Stable
Classifier: Operating System :: OS Independent
Classifier: Intended Audience :: Developers
Classifier: Intended Audience :: Information Technology
Classifier: Programming Language :: Python
Classifier: Programming Language :: Python :: 3
Classifier: Programming Language :: Python :: 3.9
Classifier: Programming Language :: Python :: 3.10
Classifier: Programming Language :: Python :: 3.11
Classifier: Programming Language :: Python :: 3.12
Classifier: Programming Language :: Python :: 3.13
Classifier: Programming Language :: Python :: 3 :: Only
Classifier: Topic :: Internet :: WWW/HTTP :: Session
Classifier: Topic :: Software Development :: Libraries :: Python Modules
Classifier: Topic :: Internet
Classifier: Typing :: Typed
Classifier: Framework :: Flask
Classifier: Framework :: FastAPI
Requires-Python: >=3.9
License-File: LICENSE.md
Requires-Dist: pycryptodome<4.0.0,>=3.21.0
Requires-Dist: cryptography<45.0.0,>=44.0.2
Provides-Extra: redis
Requires-Dist: redis>=6.4.0; extra == "redis"
Provides-Extra: json
Requires-Dist: tinydb>=4.8.2; extra == "json"
Provides-Extra: yaml
Requires-Dist: pyyaml>=6.0.2; extra == "yaml"
Provides-Extra: toml
Requires-Dist: toml>=0.10.2; extra == "toml"
Provides-Extra: litestar
Requires-Dist: litestar>=2.18.0; extra == "litestar"
Provides-Extra: starlette
Requires-Dist: starlette>=0.48.0; extra == "starlette"
Provides-Extra: fastapi
Requires-Dist: fastapi>=0.119.0; extra == "fastapi"
Provides-Extra: flask
Requires-Dist: flask>=3.1.2; extra == "flask"
Dynamic: license-file
